zconcurrent/__init__.py
zconcurrent/zsession.py
zconcurrent-0.0.2a0.dist-info/LICENSE
zconcurrent-0.0.2a0.dist-info/METADATA
zconcurrent-0.0.2a0.dist-info/WHEEL
zconcurrent-0.0.2a0.dist-info/RECORD
