Metadata-Version: 2.1
Name: zconcurrent
Version: 0.0.2a0
Summary: 
Home-page: https://github.com/fullerzz/zConcurrent
License: MIT
Author: Zach Fuller
Author-email: zach.fuller1222@gmail.com
Requires-Python: >=3.10,<4.0
Classifier: License :: OSI Approved :: MIT License
Classifier: Programming Language :: Python :: 3
Classifier: Programming Language :: Python :: 3.10
Classifier: Programming Language :: Python :: 3.11
Classifier: Programming Language :: Python :: 3.12
Provides-Extra: uvloop
Requires-Dist: aiodns (>=3.1.1,<3.2.0)
Requires-Dist: aiohttp (>=3.8.0,<3.9.0)
Requires-Dist: msgspec (==0.18.4)
Requires-Dist: uvloop (==0.19.0) ; extra == "uvloop"
Project-URL: Repository, https://github.com/fullerzz/zConcurrent
